cli/__init__.py
cli/commands.py
config/__init__.py
config/manager.py
config/validator.py
core/__init__.py
core/analyzer.py
core/base.py
core/inspector.py
core/integration.py
core/mapper.py
core/profiler.py
core/recovery.py
integrations/__init__.py
integrations/aider_runner.py
utils/__init__.py
utils/code_parser.py
utils/formatters.py
utils/memory_tracker.py
utils/metrics.py
utils/profiler.py
utils/progress.py
utils/resource_manager.py
debugai-0.1.0.dist-info/LICENSE
debugai-0.1.0.dist-info/METADATA
debugai-0.1.0.dist-info/WHEEL
debugai-0.1.0.dist-info/entry_points.txt
debugai-0.1.0.dist-info/top_level.txt
debugai-0.1.0.dist-info/RECORD
